streamlit_letsplot/__init__.py
streamlit_letsplot-0.0.3.dist-info/LICENSE
streamlit_letsplot-0.0.3.dist-info/METADATA
streamlit_letsplot-0.0.3.dist-info/WHEEL
streamlit_letsplot-0.0.3.dist-info/top_level.txt
streamlit_letsplot-0.0.3.dist-info/RECORD
